flattenpy/__init__.py
flattenpy/__main__.py
flattenpy-0.2.dist-info/METADATA
flattenpy-0.2.dist-info/WHEEL
flattenpy-0.2.dist-info/entry_points.txt
flattenpy-0.2.dist-info/top_level.txt
flattenpy-0.2.dist-info/RECORD
