Metadata-Version: 2.1
Name: flattenpy
Version: 0.2
Summary: Flatten python scripts into a single file
Author: Illia Ovcharenko
Author-email: elijah.ovcharenko@gmail.com
Requires-Python: >=3.7
Requires-Dist: astunparse (==1.6.3)
Requires-Dist: fire (==0.4.0)
Requires-Dist: GitPython (==3.1.31)
